glamkit
