Metadata-Version: 1.0
Name: glamkit
Version: 0.5.2
Summary: A Django toolkit for building websites for the Galleries, Libraries, Archives and Museums sector.
Home-page: http://github.com/glamkit/glamkit
Author: Thomas Ashelford
Author-email: thomas@interaction.net.au
License: UNKNOWN
Platform: UNKNOWN
Classifier: Development Status :: 4 - Beta
Classifier: Environment :: Web Environment
Classifier: Intended Audience :: Developers
Classifier: License :: OSI Approved :: BSD License
Classifier: Operating System :: OS Independent
Classifier: Programming Language :: Python
Classifier: Framework :: Django
